maleo/soma/enums/__init__.py
maleo/soma/enums/cache.py
maleo/soma/enums/cardinality.py
maleo/soma/enums/case.py
maleo/soma/enums/client.py
maleo/soma/enums/code.py
maleo/soma/enums/controller.py
maleo/soma/enums/environment.py
maleo/soma/enums/error.py
maleo/soma/enums/execution.py
maleo/soma/enums/expiration.py
maleo/soma/enums/field.py
maleo/soma/enums/hash.py
maleo/soma/enums/key.py
maleo/soma/enums/logging.py
maleo/soma/enums/operation.py
maleo/soma/enums/pagination.py
maleo/soma/enums/request.py
maleo/soma/enums/secret.py
maleo/soma/enums/service.py
maleo/soma/enums/sort.py
maleo/soma/enums/status.py
maleo/soma/enums/timestamp.py
maleo/soma/enums/token.py
maleo/soma/enums/user.py
maleo_soma_enums-0.0.7.dist-info/licenses/LICENSE
maleo_soma_enums-0.0.7.dist-info/METADATA
maleo_soma_enums-0.0.7.dist-info/WHEEL
maleo_soma_enums-0.0.7.dist-info/top_level.txt
maleo_soma_enums-0.0.7.dist-info/RECORD
